deepmg/__init__.py
deepmg/__main__.py
deepmg/experiment.py
deepmg/models_def.py
deepmg/read_results.py
deepmg/unfi_delete.py
deepmg/utils.py
deepmg/utils_deepmg.py
deepmg/vis_data.py
deepmg-1.0.33.dist-info/LICENSE
deepmg-1.0.33.dist-info/METADATA
deepmg-1.0.33.dist-info/WHEEL
deepmg-1.0.33.dist-info/top_level.txt
deepmg-1.0.33.dist-info/RECORD
