Metadata-Version: 2.1
Name: deepmg
Version: 1.0.33
Summary: A python package to visualize/train/predict data using machine/deep learning algorithms
Home-page: https://git.integromics.fr/published/deepmg
Author: Thanh-Hai Nguyen
Author-email: hainguyen579@gmail.com
License: GPLv3+
Platform: UNKNOWN
Classifier: Programming Language :: Python :: 3
Classifier: License :: OSI Approved :: GNU General Public License (GPL)
Classifier: Operating System :: OS Independent
